hdl/cpu/alu.v
/**
 * @file alu.v
 * @author EPSILON0-dev (lforenc@wp.pl)
 * @brief ALU + Barrel Shifter
 * @date 2022-04-30
 *
 * "7 - 2 = 4" ~ GIGACHAD
 *
 */

module alu (
    input  [31:0] in_a,
    input  [31:0] in_b,
    input  [ 2:0] funct3,
    input         funct7_4,
    input         alu_en,
    input         alu_imm,
    output [31:0] alu_out);


    /////////////////////////////////////////////////////////////////////////
    // Adder/subtractor
    /////////////////////////////////////////////////////////////////////////
    wire        op_subtract;
    wire [31:0] adder_in_b;
    wire [31:0] adder_out;

    assign op_subtract = alu_en && !alu_imm && funct7_4;
    assign adder_in_b = (op_subtract) ? ~in_b : in_b;
    assign adder_out = in_a + adder_in_b + {31'd0, op_subtract};


    /////////////////////////////////////////////////////////////////////////
    // Barrel shifter
    /////////////////////////////////////////////////////////////////////////
    wire op_sll;
    wire op_srl;
    wire op_sra;
    wire [ 4:0] shift_amount;
    wire [31:0] shift_mask;
    wire [31:0] shift_out;
    wire [31:0] shift_sll;
    wire [31:0] shift_srl;
    wire [31:0] shift_sra;
    wire [31:0] shift_combined;

    // Shifter
    alu_shifter shifter (
        .shift   (shift_amount),
        .in_val  (in_a),
        .out_val (shift_out)
    );

    // Mask
    alu_mask_lut mask_lut (
        .shift (shift_amount),
        .mask  (shift_mask)
    );

    // Operation decoder
    assign op_sll = alu_en && (funct3 == 3'b001);
    assign op_srl = alu_en && (funct3 == 3'b101) && !funct7_4;
    assign op_sra = alu_en && (funct3 == 3'b101) &&  funct7_4;
    assign shift_amount = (op_sll) ? in_b[4:0] : (5'd0 - in_b[4:0]);

    // Shift "postprocessing"
    assign shift_sll = shift_out & ~shift_mask;
    assign shift_srl = shift_out & shift_mask;
    assign shift_sra = shift_srl | (~shift_mask & {32{in_a[31]}});

    // Final shift mux
    assign shift_combined = (|shift_amount)?
        ((op_sra)? shift_sra : (op_srl)? shift_srl : shift_sll) : in_a;


    /////////////////////////////////////////////////////////////////////////
    // Logic operators
    /////////////////////////////////////////////////////////////////////////
    wire [31:0] logic_xor;
    wire [31:0] logic_or;
    wire [31:0] logic_and;

    assign logic_xor = in_a ^ in_b;
    assign logic_or  = in_a | in_b;
    assign logic_and = in_a & in_b;


    /////////////////////////////////////////////////////////////////////////
    // Signed/unsigned comparator
    /////////////////////////////////////////////////////////////////////////
    wire [31:0] comp_signed;
    wire [31:0] comp_unsigned;

    assign comp_signed   = {31'd0, (  $signed(in_a) <   $signed(in_b))};
    assign comp_unsigned = {31'd0, ($unsigned(in_a) < $unsigned(in_b))};


    /////////////////////////////////////////////////////////////////////////
    // Final mux
    /////////////////////////////////////////////////////////////////////////
    wire [31:0] mux_01, mux_23, mux_45, mux_67;
    wire [31:0] mux_03, mux_47;
    wire [31:0] mux_07;

    assign mux_01 = (funct3[0] && alu_en) ? shift_combined : adder_out;
    assign mux_23 = (funct3[0] && alu_en) ? comp_unsigned  : comp_signed;
    assign mux_45 = (funct3[0] && alu_en) ? shift_combined : logic_xor;
    assign mux_67 = (funct3[0] && alu_en) ? logic_and      : logic_or;

    assign mux_03 = (funct3[1] && alu_en) ? mux_23 : mux_01;
    assign mux_47 = (funct3[1] && alu_en) ? mux_67 : mux_45;

    assign mux_07 = (funct3[2] && alu_en) ? mux_47 : mux_03;


    /////////////////////////////////////////////////////////////////////////
    // Output assignment
    /////////////////////////////////////////////////////////////////////////
    assign alu_out = mux_07;

endmodule



/////////////////////////////////////////////////////////////////////////////
// This module is the actual barrel shifter implemented with "case"
/////////////////////////////////////////////////////////////////////////////
module alu_shifter (
    input      [ 4:0] shift,
    input      [31:0] in_val,
    output reg [31:0] out_val);

    always @* begin
        case (shift)
            default: out_val = in_val;
            5'h01:   out_val = {in_val[30:0], in_val[31]};
            5'h02:   out_val = {in_val[29:0], in_val[31:30]};
            5'h03:   out_val = {in_val[28:0], in_val[31:29]};
            5'h04:   out_val = {in_val[27:0], in_val[31:28]};
            5'h05:   out_val = {in_val[26:0], in_val[31:27]};
            5'h06:   out_val = {in_val[25:0], in_val[31:26]};
            5'h07:   out_val = {in_val[24:0], in_val[31:25]};
            5'h08:   out_val = {in_val[23:0], in_val[31:24]};
            5'h09:   out_val = {in_val[22:0], in_val[31:23]};
            5'h0A:   out_val = {in_val[21:0], in_val[31:22]};
            5'h0B:   out_val = {in_val[20:0], in_val[31:21]};
            5'h0C:   out_val = {in_val[19:0], in_val[31:20]};
            5'h0D:   out_val = {in_val[18:0], in_val[31:19]};
            5'h0E:   out_val = {in_val[17:0], in_val[31:18]};
            5'h0F:   out_val = {in_val[16:0], in_val[31:17]};
            5'h10:   out_val = {in_val[15:0], in_val[31:16]};
            5'h11:   out_val = {in_val[14:0], in_val[31:15]};
            5'h12:   out_val = {in_val[13:0], in_val[31:14]};
            5'h13:   out_val = {in_val[12:0], in_val[31:13]};
            5'h14:   out_val = {in_val[11:0], in_val[31:12]};
            5'h15:   out_val = {in_val[10:0], in_val[31:11]};
            5'h16:   out_val = {in_val[9:0], in_val[31:10]};
            5'h17:   out_val = {in_val[8:0], in_val[31:9]};
            5'h18:   out_val = {in_val[7:0], in_val[31:8]};
            5'h19:   out_val = {in_val[6:0], in_val[31:7]};
            5'h1A:   out_val = {in_val[5:0], in_val[31:6]};
            5'h1B:   out_val = {in_val[4:0], in_val[31:5]};
            5'h1C:   out_val = {in_val[3:0], in_val[31:4]};
            5'h1D:   out_val = {in_val[2:0], in_val[31:3]};
            5'h1E:   out_val = {in_val[1:0], in_val[31:2]};
            5'h1F:   out_val = {in_val[0], in_val[31:1]};
        endcase
    end

endmodule



/////////////////////////////////////////////////////////////////////////////
// This module contains the LUT for the shift mask
/////////////////////////////////////////////////////////////////////////////
module alu_mask_lut (
    input      [ 4:0] shift,
    output reg [31:0] mask);

    always @* begin
        case (shift)
            default: mask = 32'h00000000;
            5'h01:   mask = 32'h00000001;
            5'h02:   mask = 32'h00000003;
            5'h03:   mask = 32'h00000007;
            5'h04:   mask = 32'h0000000F;
            5'h05:   mask = 32'h0000001F;
            5'h06:   mask = 32'h0000003F;
            5'h07:   mask = 32'h0000007F;
            5'h08:   mask = 32'h000001FF;
            5'h09:   mask = 32'h000001FF;
            5'h0A:   mask = 32'h000003FF;
            5'h0B:   mask = 32'h000007FF;
            5'h0C:   mask = 32'h00000FFF;
            5'h0D:   mask = 32'h00001FFF;
            5'h0E:   mask = 32'h00003FFF;
            5'h0F:   mask = 32'h00007FFF;
            5'h10:   mask = 32'h0000FFFF;
            5'h11:   mask = 32'h0001FFFF;
            5'h12:   mask = 32'h0003FFFF;
            5'h13:   mask = 32'h0007FFFF;
            5'h14:   mask = 32'h000FFFFF;
            5'h15:   mask = 32'h001FFFFF;
            5'h16:   mask = 32'h003FFFFF;
            5'h17:   mask = 32'h007FFFFF;
            5'h18:   mask = 32'h00FFFFFF;
            5'h19:   mask = 32'h01FFFFFF;
            5'h1A:   mask = 32'h03FFFFFF;
            5'h1B:   mask = 32'h07FFFFFF;
            5'h1C:   mask = 32'h0FFFFFFF;
            5'h1D:   mask = 32'h1FFFFFFF;
            5'h1E:   mask = 32'h3FFFFFFF;
            5'h1F:   mask = 32'h7FFFFFFF;
        endcase
    end

endmodule

hdl/cpu/alu_tb.v
/**
 * @file alu_tb.v
 * @author EPSILON0-dev (lforenc@wp.pl)
 * @brief TB for alu.v
 * @date 2022-04-30
 *
 * "7 - 2 = 4" ~ GIGACHAD
 *
 */

`include "alu.v"
//`define DUMP

module alu_tb;

    /**
     * Test Array
     */
    parameter arr_sizes = 48;
    reg  [31:0] lut_in_a[0:arr_sizes-1];
    reg  [31:0] lut_in_b[0:arr_sizes-1];
    reg  [31:0] lut_result[0:arr_sizes-1];

    /**
     * Enable dump file if defined
     */
    `ifdef DUMP
    initial begin
        $dumpfile("alu.vcd");
        $dumpvars(0, DUT);
    end
    `endif

    /**
     * Device under test
     */
    reg  [31:0] in_a;
    reg  [31:0] in_b;
    reg  [ 2:0] funct3;
    reg         funct7_4;
    reg         alu_en;
    reg         alu_imm;
    wire [31:0] alu_out;
    wire test_res;

    alu DUT (
        .in_a     (in_a),
        .in_b     (in_b),
        .funct3   (funct3),
        .funct7_4 (funct7_4),
        .alu_en   (alu_en),
        .alu_imm  (alu_imm),
        .alu_out  (alu_out)
    );

    // verilator lint_off WIDTH
    assign test_res = (alu_out == lut_result[$time]);

    always begin
        in_a = lut_in_a[$time];
        in_b = lut_in_b[$time];
        $monitor("%d,\t%h,\t%h,\t%h,\t%b", $time, in_a, in_b, alu_out, test_res);
        #1;
    end
    // verilator lint_on WIDTH

    // This fixes undefined state at time 0
    initial begin
        in_a = 0;
        in_b = 0;
    end

    /**
     * Test Cases
     */
    initial begin
        $display("\n\n\t\t\t\t----==== ADD ====----");
        $display("\t\ttime\tin_a,\t\tin_b,\t\tout,\t\tresult");
        funct3 = 0;
        funct7_4 = 0;
        alu_en = 1;
        alu_imm = 0;

        lut_in_a[0] = 32'd0;
        lut_in_b[0] = 32'd0;
        lut_result[0] = 32'd0;

        lut_in_a[1] = 32'd1;
        lut_in_b[1] = 32'd1;
        lut_result[1] = 32'd2;

        lut_in_a[2] = 32'd3;
        lut_in_b[2] = 32'd7;
        lut_result[2] = 32'd10;

        lut_in_a[3] = 32'h00000000;
        lut_in_b[3] = 32'hffff8000;
        lut_result[3] = 32'hffff8000;

        lut_in_a[4] = 32'h80000000;
        lut_in_b[4] = 32'h00000000;
        lut_result[4] = 32'h80000000;

        lut_in_a[5] = 32'hffff8000;
        lut_in_b[5] = 32'h80000000;
        lut_result[5] = 32'h7fff8000;

        lut_in_a[6] = 32'hFFFFFFFF;
        lut_in_b[6] = 32'h00000001;
        lut_result[6] = 32'h00000000;

        lut_in_a[7] = 32'h00000001;
        lut_in_b[7] = 32'h7FFFFFFF;
        lut_result[7] = 32'h80000000;

        #8;

        $display("\n\n\t\t\t\t----==== SUB ====----");
        $display("\t\ttime\tin_a,\t\tin_b,\t\tout,\t\tresult");
        funct3 = 0;
        funct7_4 = 1;
        alu_en = 1;
        alu_imm = 0;

        lut_in_a[8] = 32'd0;
        lut_in_b[8] = 32'd0;
        lut_result[8] = 32'd0;

        lut_in_a[9] = 32'd1;
        lut_in_b[9] = 32'd1;
        lut_result[9] = 32'd0;

        lut_in_a[10] = 32'd3;
        lut_in_b[10] = 32'd7;
        lut_result[10] = 32'hfffffffc;

        lut_in_a[11] = 32'h00000000;
        lut_in_b[11] = 32'hffffffff;
        lut_result[11] = 32'h00000001;

        #4;

        $display("\n\n\t\t\t\t----==== SLL ====----");
        $display("\t\ttime\tin_a,\t\tin_b,\t\tout,\t\tresult");
        funct3 = 1;
        funct7_4 = 0;
        alu_en = 1;
        alu_imm = 0;

        lut_in_a[12] = 32'h21212121;
        lut_in_b[12] = 32'd0;
        lut_result[12] = 32'h21212121;

        lut_in_a[13] = 32'h21212121;
        lut_in_b[13] = 32'd1;
        lut_result[13] = 32'h42424242;

        lut_in_a[14] = 32'h21212121;
        lut_in_b[14] = 32'd14;
        lut_result[14] = 32'h48484000;

        lut_in_a[15] = 32'h21212121;
        lut_in_b[15] = 32'd31;
        lut_result[15] = 32'h80000000;

        #4;

        $display("\n\n\t\t\t\t----==== SLT ====----");
        $display("\t\ttime\tin_a,\t\tin_b,\t\tout,\t\tresult");
        funct3 = 2;
        funct7_4 = 0;
        alu_en = 1;
        alu_imm = 0;

        lut_in_a[16] = 32'h80000001;
        lut_in_b[16] = 32'h00000001;
        lut_result[16] = 32'h00000001;

        lut_in_a[17] = 32'h00000001;
        lut_in_b[17] = 32'h00000003;
        lut_result[17] = 32'h00000001;

        lut_in_a[18] = 32'h00000007;
        lut_in_b[18] = 32'h00000003;
        lut_result[18] = 32'h00000000;

        lut_in_a[19] = 32'hffffffff;
        lut_in_b[19] = 32'h7fffffff;
        lut_result[19] = 32'h00000001;

        #4;

        $display("\n\n\t\t\t\t----==== SLTU ====----");
        $display("\t\ttime\tin_a,\t\tin_b,\t\tout,\t\tresult");
        funct3 = 3;
        funct7_4 = 0;
        alu_en = 1;
        alu_imm = 0;

        lut_in_a[20] = 32'h80000000;
        lut_in_b[20] = 32'h00000001;
        lut_result[20] = 32'h00000000;

        lut_in_a[21] = 32'h00000001;
        lut_in_b[21] = 32'h00000003;
        lut_result[21] = 32'h00000001;

        lut_in_a[22] = 32'h00000007;
        lut_in_b[22] = 32'h00000003;
        lut_result[22] = 32'h00000000;

        lut_in_a[23] = 32'hffffffff;
        lut_in_b[23] = 32'h7fffffff;
        lut_result[23] = 32'h00000000;

        #4;

        $display("\n\n\t\t\t\t----==== XOR ====----");
        $display("\t\ttime\tin_a,\t\tin_b,\t\tout,\t\tresult");
        funct3 = 4;
        funct7_4 = 0;
        alu_en = 1;
        alu_imm = 0;

        lut_in_a[24] = 32'hff00ff00;
        lut_in_b[24] = 32'hf00ff00f;
        lut_result[24] = 32'h0f0f0f0f;

        lut_in_a[25] = 32'h0ff00ff0;
        lut_in_b[25] = 32'hff00ff00;
        lut_result[25] = 32'hf0f0f0f0;

        lut_in_a[26] = 32'h00ff00ff;
        lut_in_b[26] = 32'h0ff00ff0;
        lut_result[26] = 32'h0f0f0f0f;

        lut_in_a[27] = 32'hf00ff00f;
        lut_in_b[27] = 32'h00ff00ff;
        lut_result[27] = 32'hf0f0f0f0;

        #4;

        $display("\n\n\t\t\t\t----==== SRL ====----");
        $display("\t\ttime\tin_a,\t\tin_b,\t\tout,\t\tresult");
        funct3 = 5;
        funct7_4 = 0;
        alu_en = 1;
        alu_imm = 0;

        lut_in_a[28] = 32'h80000001;
        lut_in_b[28] = 32'd0;
        lut_result[28] = 32'h80000001;

        lut_in_a[29] = 32'h80000001;
        lut_in_b[29] = 32'd1;
        lut_result[29] = 32'h40000000;

        lut_in_a[30] = 32'h80000001;
        lut_in_b[30] = 32'd14;
        lut_result[30] = 32'h00020000;

        lut_in_a[31] = 32'h80000001;
        lut_in_b[31] = 32'd31;
        lut_result[31] = 32'h00000001;

        #4;

        $display("\n\n\t\t\t\t----==== SRA ====----");
        $display("\t\ttime\tin_a,\t\tin_b,\t\tout,\t\tresult");
        funct3 = 5;
        funct7_4 = 1;
        alu_en = 1;
        alu_imm = 0;

        lut_in_a[32] = 32'h80000001;
        lut_in_b[32] = 32'd0;
        lut_result[32] = 32'h80000001;

        lut_in_a[33] = 32'h80000001;
        lut_in_b[33] = 32'd1;
        lut_result[33] = 32'hC0000000;

        lut_in_a[34] = 32'h40000001;
        lut_in_b[34] = 32'd30;
        lut_result[34] = 32'h00000001;

        lut_in_a[35] = 32'h80000001;
        lut_in_b[35] = 32'd30;
        lut_result[35] = 32'hFFFFFFFE;

        #4;

        $display("\n\n\t\t\t\t----==== OR ====----");
        $display("\t\ttime\tin_a,\t\tin_b,\t\tout,\t\tresult");
        funct3 = 6;
        funct7_4 = 0;
        alu_en = 1;
        alu_imm = 0;

        lut_in_a[36] = 32'hff00ff00;
        lut_in_b[36] = 32'h0f0f0f0f;
        lut_result[36] = 32'hff0fff0f;

        lut_in_a[37] = 32'h0ff00ff0;
        lut_in_b[37] = 32'hf0f0f0f0;
        lut_result[37] = 32'hfff0fff0;

        lut_in_a[38] = 32'h00ff00ff;
        lut_in_b[38] = 32'h0f0f0f0f;
        lut_result[38] = 32'h0fff0fff;

        lut_in_a[39] = 32'hf00ff00f;
        lut_in_b[39] = 32'hf0f0f0f0;
        lut_result[39] = 32'hf0fff0ff;

        #4;

        $display("\n\n\t\t\t\t----==== AND ====----");
        $display("\t\ttime\tin_a,\t\tin_b,\t\tout,\t\tresult");
        funct3 = 7;
        funct7_4 = 0;
        alu_en = 1;
        alu_imm = 0;

        lut_in_a[40] = 32'hff00ff00;
        lut_in_b[40] = 32'h0f0f0f0f;
        lut_result[40] = 32'h0f000f00;

        lut_in_a[41] = 32'h0ff00ff0;
        lut_in_b[41] = 32'hf0f0f0f0;
        lut_result[41] = 32'h00f000f0;

        lut_in_a[42] = 32'h00ff00ff;
        lut_in_b[42] = 32'h0f0f0f0f;
        lut_result[42] = 32'h000f000f;

        lut_in_a[43] = 32'hf00ff00f;
        lut_in_b[43] = 32'hf0f0f0f0;
        lut_result[43] = 32'hf000f000;

        #4;

        $display("\n\n\t\t\t\t----==== NONE ====----");
        $display("\t\ttime\tin_a,\t\tin_b,\t\tout,\t\tresult");
        funct3 = 7;
        funct7_4 = 1;
        alu_en = 0;
        alu_imm = 1;

        lut_in_a[44] = 32'd0;
        lut_in_b[44] = 32'd0;
        lut_result[44] = 32'd0;

        lut_in_a[45] = 32'd1;
        lut_in_b[45] = 32'd1;
        lut_result[45] = 32'd2;

        lut_in_a[46] = 32'd3;
        lut_in_b[46] = 32'd7;
        lut_result[46] = 32'd10;

        lut_in_a[47] = 32'h00000000;
        lut_in_b[47] = 32'hffff8000;
        lut_result[47] = 32'hffff8000;

        #4 $finish;

    end

endmodule

hdl/cpu/alu.vcd
$date
	Sat Apr 30 16:02:24 2022
$end
$version
	Icarus Verilog
$end
$timescale
	1s
$end
$scope module alu_tb $end
$scope module DUT $end
$var wire 1 ! alu_en $end
$var wire 1 " alu_imm $end
$var wire 32 # alu_out [31:0] $end
$var wire 3 $ funct3 [2:0] $end
$var wire 1 % funct7_4 $end
$var wire 32 & in_a [31:0] $end
$var wire 32 ' in_b [31:0] $end
$var wire 32 ( logic_and [31:0] $end
$var wire 32 ) logic_or [31:0] $end
$var wire 32 * logic_xor [31:0] $end
$var wire 1 + op_sll $end
$var wire 1 , op_sra $end
$var wire 1 - op_srl $end
$var wire 1 . op_subtract $end
$var wire 32 / shift_sll [31:0] $end
$var wire 32 0 shift_sra [31:0] $end
$var wire 32 1 shift_srl [31:0] $end
$var wire 32 2 shift_combined [31:0] $end
$var wire 5 3 shift_amount [4:0] $end
$var wire 32 4 mux_67 [31:0] $end
$var wire 32 5 mux_47 [31:0] $end
$var wire 32 6 mux_45 [31:0] $end
$var wire 32 7 mux_23 [31:0] $end
$var wire 32 8 mux_07 [31:0] $end
$var wire 32 9 mux_03 [31:0] $end
$var wire 32 : mux_01 [31:0] $end
$var wire 32 ; comp_unsigned [31:0] $end
$var wire 32 < comp_signed [31:0] $end
$var wire 32 = adder_out [31:0] $end
$var wire 32 > adder_in_b [31:0] $end
$var reg 32 ? shift_mask [31:0] $end
$var reg 32 @ shift_out [31:0] $end
$upscope $end
$upscope $end
$enddefinitions $end
#0
$dumpvars
b0 @
b0 ?
b0 >
b0 =
b0 <
b0 ;
b0 :
b0 9
b0 8
b0 7
b0 6
b0 5
b0 4
b0 3
b0 2
b0 1
b0 0
b0 /
0.
0-
0,
0+
b0 *
b0 )
b0 (
b0 '
b0 &
0%
b0 $
b0 #
0"
1!
$end
#1
b1111111111111111111111111111111 ?
b10 #
b10 8
b11111 3
b1 4
b10000000000000000000000000000000 /
b10 9
b1 >
b1 )
b1 (
b10000000000000000000000000000000 @
b10 :
b10000000000000000000000000000000 2
b1 '
b10 =
b1 &
#2
b110000000000000000000000000 2
b110000000000000000000000000 /
b1111111111111111111111111 ?
b100 5
b0 0
b1010 #
b1010 8
b11001 3
b100 6
b111 4
b0 1
b1010 9
b111 >
b1 7
b100 *
b111 )
b11 (
b110000000000000000000000000 @
b1010 :
b1 <
b1 ;
b111 '
b1010 =
b11 &
#3
b0 2
b0 ?
b11111111111111111000000000000000 5
b11111111111111111000000000000000 #
b11111111111111111000000000000000 8
b0 3
b11111111111111111000000000000000 6
b11111111111111111000000000000000 4
b0 /
b11111111111111111000000000000000 9
b11111111111111111000000000000000 >
b0 7
b11111111111111111000000000000000 *
b11111111111111111000000000000000 )
b0 (
b0 @
b11111111111111111000000000000000 :
b0 <
b11111111111111111000000000000000 '
b11111111111111111000000000000000 =
b0 &
#4
b10000000000000000000000000000000 5
b10000000000000000000000000000000 #
b10000000000000000000000000000000 8
b11111111111111111111111111111111 0
b10000000000000000000000000000000 6
b10000000000000000000000000000000 4
b10000000000000000000000000000000 /
b10000000000000000000000000000000 9
b0 >
b10000000000000000000000000000000 *
b10000000000000000000000000000000 )
b10000000000000000000000000000000 @
b10000000000000000000000000000000 :
b10000000000000000000000000000000 2
b1 7
b0 ;
b0 '
b10000000000000000000000000000000 =
b1 <
b10000000000000000000000000000000 &
#5
b1111111111111111000000000000000 5
b1111111111111111000000000000000 #
b1111111111111111000000000000000 8
b1111111111111111000000000000000 6
b11111111111111111000000000000000 4
b11111111111111111000000000000000 /
b1111111111111111000000000000000 9
b10000000000000000000000000000000 >
b0 7
b1111111111111111000000000000000 *
b11111111111111111000000000000000 )
b10000000000000000000000000000000 (
b11111111111111111000000000000000 @
b1111111111111111000000000000000 :
b11111111111111111000000000000000 2
b0 <
b10000000000000000000000000000000 '
b1111111111111111000000000000000 =
b11111111111111111000000000000000 &
#6
b1111111111111111111111111111111 1
b1111111111111111111111111111111 ?
b11111111111111111111111111111110 5
b0 #
b0 8
b11111 3
b11111111111111111111111111111110 6
b11111111111111111111111111111111 4
b10000000000000000000000000000000 /
b0 9
b1 >
b1 7
b11111111111111111111111111111110 *
b11111111111111111111111111111111 )
b1 (
b11111111111111111111111111111111 @
b0 :
b10000000000000000000000000000000 2
b1 <
b1 '
b0 =
b11111111111111111111111111111111 &
#7
b10 2
b10 /
b1 ?
b1111111111111111111111111111110 5
b10000000000000000000000000000000 #
b10000000000000000000000000000000 8
b0 0
b1 3
b1111111111111111111111111111110 6
b1111111111111111111111111111111 4
b0 1
b10000000000000000000000000000000 9
b1111111111111111111111111111111 >
b1111111111111111111111111111110 *
b1111111111111111111111111111111 )
b10 @
b10000000000000000000000000000000 :
b1 ;
b1111111111111111111111111111111 '
b10000000000000000000000000000000 =
b1 <
b1 &
#8
b0 #
b0 8
b0 9
b0 2
b0 ?
b0 5
b0 :
b0 3
b0 6
b0 4
b0 /
b11111111111111111111111111111111 >
b0 7
b0 *
b0 )
b0 (
b0 @
1.
b0 <
b0 ;
b0 '
b0 =
b0 &
1%
#9
b1111111111111111111111111111111 ?
b0 #
b0 8
b11111111111111111111111111111110 >
b11111 3
b1 4
b10000000000000000000000000000000 /
b0 9
b1 )
b1 (
b10000000000000000000000000000000 @
b0 :
b10000000000000000000000000000000 2
b1 '
b0 =
b1 &
#10
b110000000000000000000000000 2
b110000000000000000000000000 /
b1111111111111111111111111 ?
b100 5
b0 0
b11111111111111111111111111111100 #
b11111111111111111111111111111100 8
b11111111111111111111111111111000 >
b11001 3
b100 6
b111 4
b0 1
b11111111111111111111111111111100 9
b1 7
b100 *
b111 )
b11 (
b110000000000000000000000000 @
b11111111111111111111111111111100 :
b1 <
b1 ;
b111 '
b11111111111111111111111111111100 =
b11 &
#11
b0 2
b1 ?
b11111111111111111111111111111111 5
b1 #
b1 8
b0 >
b1 3
b11111111111111111111111111111111 6
b11111111111111111111111111111111 4
b0 /
b1 9
b0 7
b11111111111111111111111111111111 *
b11111111111111111111111111111111 )
b0 (
b0 @
b1 :
b0 <
b11111111111111111111111111111111 '
b1 =
b0 &
#12
b100001001000010010000100100001 5
b100001001000010010000100100001 #
b100001001000010010000100100001 8
b100001001000010010000100100001 2
b0 ?
b100001001000010010000100100001 6
b0 4
b100001001000010010000100100001 /
b100001001000010010000100100001 9
b0 3
b100001001000010010000100100001 *
b100001001000010010000100100001 )
b100001001000010010000100100001 @
b100001001000010010000100100001 :
0.
1+
b0 ;
b0 '
b100001001000010010000100100001 =
b100001001000010010000100100001 &
0%
b1 $
#13
b1000010010000100100001001000010 #
b1000010010000100100001001000010 8
b1000010010000100100001001000010 9
b1000010010000100100001001000010 5
b1000010010000100100001001000010 :
b1000010010000100100001001000010 6
b1000010010000100100001001000010 2
b1000010010000100100001001000010 /
b1 ?
b1000010010000100100001001000010 @
b1 4
b1 3
b100001001000010010000100100000 *
b1 (
b100001001000010010000100100010 =
b1 >
b1 '
#14
b1001000010010000100000000000000 #
b1001000010010000100000000000000 8
b1001000010010000100000000000000 9
b1001000010010000100000000000000 5
b1001000010010000100000000000000 :
b1001000010010000100000000000000 6
b1001000010010000100000000000000 2
b100001001000 0
b100001001000 1
b1001000010010000100000000000000 /
b11111111111111 ?
b1001000010010000100100001001000 @
b0 4
b1110 3
b100001001000010010000100101111 *
b100001001000010010000100101111 )
b0 (
b100001001000010010000100101111 =
b1110 >
b1110 '
#15
b10000000000000000000000000000000 #
b10000000000000000000000000000000 8
b10000000000000000000000000000000 9
b10000000000000000000000000000000 5
b10000000000000000000000000000000 :
b10000000000000000000000000000000 6
b10000000000000000000000000000000 2
b10000100100001001000010010000 0
b10000100100001001000010010000 1
b10000000000000000000000000000000 /
b1111111111111111111111111111111 ?
b10010000100100001001000010010000 @
b1 4
b11111 3
b100001001000010010000100111110 *
b100001001000010010000100111111 )
b1 (
b100001001000010010000101000000 =
b11111 >
b11111 '
#16
b1 #
b1 8
b11000000000000000000000000000000 0
b10000000000000000000000000000010 :
b1 7
b10000000000000000000000000000001 4
b1 9
b10000000000000000000000000000001 5
b1000000000000000000000000000000 1
b1 >
b10000000000000000000000000000000 *
b10000000000000000000000000000001 )
b11000000000000000000000000000000 @
0+
b1 '
b10000000000000000000000000000010 =
b1 <
b10000000000000000000000000000001 &
b10 $
#17
b100000000000000000000000000000 2
b100000000000000000000000000000 /
b11111111111111111111111111111 ?
b11 5
b0 0
b11101 3
b10 6
b11 4
b0 1
b11 >
b10 *
b11 )
b100000000000000000000000000000 @
b100 :
b1 ;
b11 '
b100 =
b1 <
b1 &
#18
b11100000000000000000000000000000 2
b111 5
b0 #
b0 8
b100 6
b111 4
b11100000000000000000000000000000 /
b0 9
b100 *
b111 )
b11 (
b11100000000000000000000000000000 @
b1010 :
b0 7
b1010 =
b0 <
b0 ;
b111 &
#19
b11111111111111111111111111111110 2
b11111111111111111111111111111110 /
b1 ?
b11111111111111111111111111111111 5
b11111111111111111111111111111111 0
b1 #
b1 8
b1 3
b10000000000000000000000000000000 6
b11111111111111111111111111111111 4
b1 1
b1 9
b1111111111111111111111111111111 >
b10000000000000000000000000000000 *
b11111111111111111111111111111111 )
b1111111111111111111111111111111 (
b11111111111111111111111111111111 @
b1111111111111111111111111111110 :
b1 7
b1111111111111111111111111111111 '
b1111111111111111111111111111110 =
b1 <
b11111111111111111111111111111111 &
#20
b11000000000000000000000000000000 0
b0 2
b0 #
b0 8
b1000000000000000000000000000000 1
b0 9
b1111111111111111111111111111111 ?
b0 5
b0 7
b11111 3
b0 6
b0 4
b0 /
b1 >
b10000000000000000000000000000001 *
b10000000000000000000000000000001 )
b0 (
b1000000000000000000000000000000 @
b0 :
b1 '
b10000000000000000000000000000001 =
b10000000000000000000000000000000 &
b11 $
#21
b100000000000000000000000000000 :
b100000000000000000000000000000 6
b100000000000000000000000000000 2
b11111111111111111111111111111 ?
b1 #
b1 8
b1 5
b0 0
b11101 3
b1 9
b1 4
b0 1
b100000000000000000000000000000 /
b11 >
b1 7
b10 *
b11 )
b1 (
b100000000000000000000000000000 @
b1 ;
b11 '
b100 =
b1 <
b1 &
#22
b11100000000000000000000000000000 :
b11100000000000000000000000000000 6
b11100000000000000000000000000000 2
b11 5
b0 #
b0 8
b11 4
b11100000000000000000000000000000 /
b0 9
b100 *
b111 )
b11 (
b11100000000000000000000000000000 @
b0 7
b1010 =
b0 <
b0 ;
b111 &
#23
b11111111111111111111111111111110 :
b11111111111111111111111111111110 6
b11111111111111111111111111111110 2
b11111111111111111111111111111110 /
b1 ?
b1111111111111111111111111111111 5
b11111111111111111111111111111111 0
b1 3
b1111111111111111111111111111111 4
b1 1
b1111111111111111111111111111111 >
b10000000000000000000000000000000 *
b11111111111111111111111111111111 )
b1111111111111111111111111111111 (
b11111111111111111111111111111111 @
b1111111111111111111111111111111 '
b1111111111111111111111111111110 =
b1 <
b11111111111111111111111111111111 &
#24
b11111111111111111111111000000001 0
b11111110000000000000000000000000 2
b11111111000000001 1
b11111111111111111 ?
b1110000100000000111000001111 :
b1 7
b11110000000011111111000000001111 6
b1110000100000000111000001111 9
b11110000000011111111000000001111 5
b11110000000011111111000000001111 #
b11110000000011111111000000001111 8
b10001 3
b11111111000011111111111100001111 4
b11111110000000000000000000000000 /
b1111000011110000111100001111 >
b11110000000011111111000000001111 *
b11111111000011111111111100001111 )
b1111000000000000111100000000 (
b11111110000000011111111000000001 @
b1111000011110000111100001111 '
b1110000100000000111000001111 =
b11111111000000001111111100000000 &
b100 $
#25
b1111111100000000000000000000 2
b11111111000000001111111100000000 #
b11111111000000001111111100000000 8
b1111111111111111 ?
b11111111000000001111111100000000 5
b111111110000 0
b10000 3
b11111111000000001111111100000000 6
b11111111111100001111111111110000 4
b111111110000 1
b1111111100000000000000000000 /
b111000010000000011100000 9
b11110000111100001111000011110000 >
b11111111000000001111111100000000 *
b11111111111100001111111111110000 )
b111100000000000011110000 (
b1111111100000000111111110000 @
b111000010000000011100000 :
b0 7
b1 ;
b11110000111100001111000011110000 '
b111000010000000011100000 =
b0 <
b1111111100000000111111110000 &
#26
b1111111100000000000000000 2
b1111111100000000111111110000 #
b1111111100000000111111110000 8
b11111111111111111 ?
b1111111100000000111111110000 5
b111111110 0
b10001 3
b1111111100000000111111110000 6
b1111111111110000111111111111 4
b111111110 1
b1111111100000000000000000 /
b10000000011100001000000001110 9
b1111000011110000111100001111 >
b1 7
b1111111100000000111111110000 *
b1111111111110000111111111111 )
b11110000000000001111 (
b1111111100000000111111110 @
b10000000011100001000000001110 :
b1 <
b1111000011110000111100001111 '
b10000000011100001000000001110 =
b111111110000000011111111 &
